resc_helm_wizard/__init__.py
resc_helm_wizard/common.py
resc_helm_wizard/constants.py
resc_helm_wizard/helm_utilities.py
resc_helm_wizard/helm_value.py
resc_helm_wizard/kubernetes_utilities.py
resc_helm_wizard/questions.py
resc_helm_wizard/run_wizard.py
resc_helm_wizard/validator.py
resc_helm_wizard/vcs_instance.py
resc_helm_wizard/config/example-values.yaml
resc_helm_wizard-1.1.0.dist-info/LICENSE.md
resc_helm_wizard-1.1.0.dist-info/METADATA
resc_helm_wizard-1.1.0.dist-info/WHEEL
resc_helm_wizard-1.1.0.dist-info/entry_points.txt
resc_helm_wizard-1.1.0.dist-info/top_level.txt
resc_helm_wizard-1.1.0.dist-info/RECORD
