Metadata-Version: 2.1
Name: resc_helm_wizard
Version: 1.1.0
Summary: Repository Scanner - Helm Wizard
Home-page: https://github.com/ABNAMRO/repository-scanner
Download-URL: 
Author: ABN AMRO
Author-email: resc@nl.abnamro.com
Requires-Python: >=3.12
License-File: LICENSE.md
Requires-Dist: questionary ==2.0.1
Requires-Dist: requests ==2.31.0
Requires-Dist: PyYAML ==6.0.1
Requires-Dist: setuptools <=69.5.1
